plexer.py
plexer-1.1.0.dist-info/LICENSE
plexer-1.1.0.dist-info/WHEEL
plexer-1.1.0.dist-info/METADATA
plexer-1.1.0.dist-info/RECORD
